[
  {
    "assetId": "limestone wall",
    "layerId": "layer_0",
    "position": {
      "x": 109,
      "y": 0,
      "z": 149
    },
    "rotation": {
      "x": 0,
      "y": 1.5707963267948966,
      "z": 0
    },
    "scale": {
      "x": 1,
      "y": 1,
      "z": 1
    }
  },
  {
    "assetId": "limestone wall",
    "layerId": "layer_0",
    "position": {
      "x": 110,
      "y": 0.02483735872492865,
      "z": 148
    },
    "rotation": {
      "x": 0,
      "y": 3.141592653589793,
      "z": 0
    },
    "scale": {
      "x": 1,
      "y": 1,
      "z": 1
    }
  },
  {
    "assetId": "limestone wall",
    "layerId": "layer_0",
    "position": {
      "x": 112,
      "y": 0.02483735872492865,
      "z": 148
    },
    "rotation": {
      "x": 0,
      "y": 3.141592653589793,
      "z": 0
    },
    "scale": {
      "x": 1,
      "y": 1,
      "z": 1
    }
  },
  {
    "assetId": "limestone wall",
    "layerId": "layer_0",
    "position": {
      "x": 109.5,
      "y": 0,
      "z": 151
    },
    "rotation": {
      "x": 0,
      "y": 2.0943951023931957,
      "z": 0
    },
    "scale": {
      "x": 1.15,
      "y": 0.9999999999999999,
      "z": 0.9999999999999999
    }
  },
  {
    "assetId": "limestone wall",
    "layerId": "layer_0",
    "position": {
      "x": 113,
      "y": 8.881784197001252e-16,
      "z": 149
    },
    "rotation": {
      "x": 0,
      "y": -1.570796326794897,
      "z": 0
    },
    "scale": {
      "x": 1,
      "y": 1,
      "z": 1
    }
  },
  {
    "assetId": "limestone wall",
    "layerId": "layer_0",
    "position": {
      "x": 113,
      "y": 8.881784197001252e-16,
      "z": 151
    },
    "rotation": {
      "x": 0,
      "y": 1.5707963267948961,
      "z": 0
    },
    "scale": {
      "x": 1,
      "y": 1,
      "z": 1
    }
  },
  {
    "assetId": "limestone doorframe",
    "layerId": "layer_0",
    "position": {
      "x": 111.5,
      "y": 0,
      "z": 152
    },
    "rotation": {
      "x": 0,
      "y": 0,
      "z": 0
    },
    "scale": {
      "x": 1.4499999999999997,
      "y": 0.9999999999999999,
      "z": 0.9999999999999999
    }
  },
  {
    "assetId": "basicTruedoor",
    "layerId": "layer_0",
    "position": {
      "x": 111.5,
      "y": 8.881784197001252e-16,
      "z": 152
    },
    "rotation": {
      "x": 6.162975822039155e-33,
      "y": 1.5707963267948963,
      "z": 1.1102230246251568e-16
    },
    "scale": {
      "x": 1,
      "y": 0.9999999999999999,
      "z": 1
    }
  },
  {
    "assetId": "Fence2",
    "layerId": "layer_0",
    "position": {
      "x": 113.5,
      "y": -4.440892098500626e-16,
      "z": 152
    },
    "rotation": {
      "x": 0,
      "y": 0,
      "z": 0
    },
    "scale": {
      "x": 1.15,
      "y": 1,
      "z": 1
    }
  },
  {
    "assetId": "onepersonbed1",
    "layerId": "layer_0",
    "position": {
      "x": 110.00539014469256,
      "y": 0,
      "z": 150.79808376978195
    },
    "rotation": {
      "x": 0,
      "y": -2.6179938779914944,
      "z": 0
    },
    "scale": {
      "x": 1,
      "y": 1,
      "z": 1
    }
  },
  {
    "assetId": "Fence2",
    "layerId": "layer_0",
    "position": {
      "x": 116,
      "y": 0,
      "z": 150.5
    },
    "rotation": {
      "x": 0,
      "y": 1.5707963267948966,
      "z": 0
    },
    "scale": {
      "x": 1.15,
      "y": 1,
      "z": 1
    }
  },
  {
    "assetId": "Fence2",
    "layerId": "layer_0",
    "position": {
      "x": 115.51598209896716,
      "y": 0,
      "z": 151.5441346392913
    },
    "rotation": {
      "x": 0,
      "y": 0.7853981633974483,
      "z": 0
    },
    "scale": {
      "x": 1.15,
      "y": 1,
      "z": 1
    }
  },
  {
    "assetId": "Fence2",
    "layerId": "layer_0",
    "position": {
      "x": 116,
      "y": 0,
      "z": 149.5
    },
    "rotation": {
      "x": 0,
      "y": 1.5707963267948966,
      "z": 0
    },
    "scale": {
      "x": 0.9999999999999999,
      "y": 1,
      "z": 1
    }
  },
  {
    "assetId": "Fence2",
    "layerId": "layer_0",
    "position": {
      "x": 116,
      "y": 8.881784197001252e-16,
      "z": 148.5
    },
    "rotation": {
      "x": 0,
      "y": 1.5707963267948966,
      "z": 0
    },
    "scale": {
      "x": 0.9999999999999999,
      "y": 1,
      "z": 1
    }
  },
  {
    "assetId": "Fence2",
    "layerId": "layer_0",
    "position": {
      "x": 115.5,
      "y": 8.881784197001252e-16,
      "z": 148
    },
    "rotation": {
      "x": 0,
      "y": 3.141592653589793,
      "z": 0
    },
    "scale": {
      "x": 0.9999999999999999,
      "y": 1,
      "z": 1
    }
  },
  {
    "assetId": "Fence2",
    "layerId": "layer_0",
    "position": {
      "x": 114.5,
      "y": -8.881784197001252e-16,
      "z": 148
    },
    "rotation": {
      "x": 0,
      "y": 3.141592653589793,
      "z": 0
    },
    "scale": {
      "x": 0.9999999999999999,
      "y": 1,
      "z": 1
    }
  },
  {
    "assetId": "Fence2",
    "layerId": "layer_0",
    "position": {
      "x": 113.5,
      "y": 0,
      "z": 148
    },
    "rotation": {
      "x": 0,
      "y": 3.141592653589793,
      "z": 0
    },
    "scale": {
      "x": 0.9999999999999999,
      "y": 1,
      "z": 1
    }
  },
  {
    "assetId": "roof corner inverse",
    "layerId": "layer_0",
    "position": {
      "x": 108.5,
      "y": 0,
      "z": 155.5
    },
    "rotation": {
      "x": 0,
      "y": 0,
      "z": 0
    },
    "scale": {
      "x": 1,
      "y": 1,
      "z": 1
    }
  },
  {
    "assetId": "tile roofing",
    "layerId": "layer_0",
    "position": {
      "x": 110.5,
      "y": 0,
      "z": 156.5
    },
    "rotation": {
      "x": 0,
      "y": 0,
      "z": 0
    },
    "scale": {
      "x": 1,
      "y": 1,
      "z": 1
    }
  },
  {
    "assetId": "roof triangle",
    "layerId": "layer_0",
    "position": {
      "x": 107.5,
      "y": 8.881784197001252e-16,
      "z": 155.5
    },
    "rotation": {
      "x": 0,
      "y": 0,
      "z": 0
    },
    "scale": {
      "x": 1,
      "y": 1,
      "z": 1
    }
  },
  {
    "assetId": "roof corner",
    "layerId": "layer_0",
    "position": {
      "x": 112.77171724092312,
      "y": 2.46,
      "z": 151.82649431524382
    },
    "rotation": {
      "x": 0,
      "y": 0,
      "z": 0
    },
    "scale": {
      "x": 1,
      "y": 1,
      "z": 1
    }
  },
  {
    "assetId": "roof",
    "layerId": "layer_0",
    "position": {
      "x": 109.5,
      "y": -8.881784197001252e-16,
      "z": 156.5
    },
    "rotation": {
      "x": 0,
      "y": 0,
      "z": 0
    },
    "scale": {
      "x": 1,
      "y": 1,
      "z": 1
    }
  },
  {
    "assetId": "roof corner",
    "layerId": "layer_0",
    "position": {
      "x": 109.06566981836475,
      "y": 2.4595315381109812,
      "z": 151.8300629659038
    },
    "rotation": {
      "x": 3.3793047749459693e-17,
      "y": -1.5707963267948966,
      "z": -4.4039957252730333e-17
    },
    "scale": {
      "x": 1,
      "y": 1,
      "z": 1
    }
  },
  {
    "assetId": "tile roofing",
    "layerId": "layer_0",
    "position": {
      "x": 111.3424576479932,
      "y": 2.459999999999998,
      "z": 152.32398828504708
    },
    "rotation": {
      "x": 0,
      "y": 0,
      "z": 0
    },
    "scale": {
      "x": 0.85,
      "y": 1,
      "z": 1
    }
  },
  {
    "assetId": "tile roofing",
    "layerId": "layer_0",
    "position": {
      "x": 110.49329163038404,
      "y": 2.459999999999998,
      "z": 152.32398828504708
    },
    "rotation": {
      "x": 0,
      "y": 0,
      "z": 0
    },
    "scale": {
      "x": 0.85,
      "y": 1,
      "z": 1
    }
  },
  {
    "assetId": "roof corner",
    "layerId": "layer_0",
    "position": {
      "x": 109.06566981836475,
      "y": 2.4595315381109812,
      "z": 148.1206161223593
    },
    "rotation": {
      "x": 3.379304774945966e-17,
      "y": -3.1415926535897927,
      "z": -4.4039957252730333e-17
    },
    "scale": {
      "x": 1,
      "y": 1,
      "z": 1
    }
  },
  {
    "assetId": "tile roofing",
    "layerId": "layer_0",
    "position": {
      "x": 108.5614718703018,
      "y": 2.459999999999999,
      "z": 150.42983630273986
    },
    "rotation": {
      "x": 0,
      "y": -1.5707963267948966,
      "z": 0
    },
    "scale": {
      "x": 0.85,
      "y": 1,
      "z": 1
    }
  },
  {
    "assetId": "tile roofing",
    "layerId": "layer_0",
    "position": {
      "x": 108.5614718703018,
      "y": 2.459999999999999,
      "z": 149.5515774209893
    },
    "rotation": {
      "x": 0,
      "y": -1.5707963267948966,
      "z": 0
    },
    "scale": {
      "x": 1,
      "y": 1,
      "z": 1
    }
  },
  {
    "assetId": "roof corner",
    "layerId": "layer_0",
    "position": {
      "x": 112.77171724092312,
      "y": 2.46,
      "z": 148.1198032818004
    },
    "rotation": {
      "x": 0,
      "y": 1.5707963267948966,
      "z": 0
    },
    "scale": {
      "x": 1,
      "y": 1,
      "z": 1
    }
  },
  {
    "assetId": "tile roofing",
    "layerId": "layer_0",
    "position": {
      "x": 113.2736299713246,
      "y": 2.459999999999999,
      "z": 149.47853824136385
    },
    "rotation": {
      "x": 0,
      "y": 1.5707963267948966,
      "z": 0
    },
    "scale": {
      "x": 0.85,
      "y": 1,
      "z": 1
    }
  },
  {
    "assetId": "tile roofing",
    "layerId": "layer_0",
    "position": {
      "x": 113.27362999340788,
      "y": 2.459999999999999,
      "z": 150.35679698099472
    },
    "rotation": {
      "x": 0,
      "y": 1.5707963267948966,
      "z": 0
    },
    "scale": {
      "x": 1,
      "y": 1,
      "z": 1
    }
  },
  {
    "assetId": "tile roofing",
    "layerId": "layer_0",
    "position": {
      "x": 111.34245757928723,
      "y": 2.459999999999998,
      "z": 147.6102167376527
    },
    "rotation": {
      "x": 0,
      "y": 3.141592653589793,
      "z": 0
    },
    "scale": {
      "x": 0.85,
      "y": 1,
      "z": 1
    }
  },
  {
    "assetId": "tile roofing",
    "layerId": "layer_0",
    "position": {
      "x": 110.49329169908998,
      "y": 2.459999999999998,
      "z": 147.61021675900454
    },
    "rotation": {
      "x": 0,
      "y": 3.141592653589793,
      "z": 0
    },
    "scale": {
      "x": 0.85,
      "y": 1,
      "z": 1
    }
  },
  {
    "assetId": "roof corner",
    "layerId": "layer_0",
    "position": {
      "x": 110.04707980837203,
      "y": 3.0195315381109813,
      "z": 149.11686591902466
    },
    "rotation": {
      "x": 3.3793047749459625e-17,
      "y": -3.141592653589793,
      "z": -4.403995725273031e-17
    },
    "scale": {
      "x": 1,
      "y": 1,
      "z": 1
    }
  },
  {
    "assetId": "roof triangle",
    "layerId": "layer_0",
    "position": {
      "x": 109.56865360373335,
      "y": 3.000000000000001,
      "z": 151.31957964664986
    },
    "rotation": {
      "x": 0,
      "y": 0,
      "z": 0
    },
    "scale": {
      "x": 1,
      "y": 1,
      "z": 1
    }
  },
  {
    "assetId": "roof corner",
    "layerId": "layer_0",
    "position": {
      "x": 111.78091986025734,
      "y": 3.0195315381109813,
      "z": 150.8292270184312
    },
    "rotation": {
      "x": 3.3793047749459656e-17,
      "y": -3.330669073875473e-16,
      "z": -4.4039957252730333e-17
    },
    "scale": {
      "x": 1,
      "y": 1,
      "z": 1
    }
  },
  {
    "assetId": "roof corner",
    "layerId": "layer_0",
    "position": {
      "x": 110.04707980837203,
      "y": 3.0195315381109813,
      "z": 150.8292270184312
    },
    "rotation": {
      "x": 3.3793047749459693e-17,
      "y": -1.5707963267948966,
      "z": -4.4039957252730333e-17
    },
    "scale": {
      "x": 1,
      "y": 1,
      "z": 1
    }
  }
]